AUTHORS
CHANGELOG
INSTALL
LICENSE
MANIFEST.in
README.rst
setup.py
python_bitrix24/__init__.py
python_bitrix24/bitrix24.py
python_bitrix24.egg-info/PKG-INFO
python_bitrix24.egg-info/SOURCES.txt
python_bitrix24.egg-info/dependency_links.txt
python_bitrix24.egg-info/not-zip-safe
python_bitrix24.egg-info/requires.txt
python_bitrix24.egg-info/top_level.txt
python_bitrix24/python_bitrix24_django/__init__.py
tests/runtests.py
tests/tests.py