Metadata-Version: 1.1
Name: python-bitrix24
Version: 0.1.1
Summary: Python Bitrix24 API
Home-page: https://github.com/moshkov/python_bitrix24
Author: Ivan Moshkov
Author-email: ivan@moshkov.pro
License: MIT License
Platform: UNKNOWN
Classifier: Development Status :: 4 - Beta
Classifier: Operating System :: OS Independent
Classifier: Programming Language :: Python
Classifier: Programming Language :: Python :: 2
Classifier: Programming Language :: Python :: 2.7
Classifier: Programming Language :: Python :: 3
Classifier: Programming Language :: Python :: 3.4
Classifier: Programming Language :: Python :: 3.5
Classifier: Programming Language :: Python :: 3.6
Classifier: License :: OSI Approved :: MIT License
